{
  "assets" : {
    "62AF68723D523CB0B6126FDD444F2106" : {
      "type" : "texture",
      "index" : 1,
      "assetRequest" : {
        "type" : "slide",
        "state" : "contents",
        "slide" : "none"
      },
      "url" : {
        "native" : "assets\/6E67FEDA-4AA9-44A9-A0A3-6E04CDAAD09C.pdf"
      },
      "width" : 101,
      "height" : 45
    },
    "AA98C6C2E266FB093DA58C988EA7197A" : {
      "type" : "texture",
      "index" : 4,
      "assetRequest" : {
        "type" : "slide",
        "state" : "contents",
        "slide" : "none"
      },
      "url" : {
        "native" : "assets\/6E67FEDA-4AA9-44A9-A0A3-6E04CDAAD09C.pdf"
      },
      "width" : 720,
      "height" : 405
    },
    "81F751BA63ED0B2F87BBFEFCA49A3BD6" : {
      "type" : "texture",
      "index" : 2,
      "assetRequest" : {
        "type" : "slide",
        "state" : "contents",
        "slide" : "none"
      },
      "url" : {
        "native" : "assets\/6E67FEDA-4AA9-44A9-A0A3-6E04CDAAD09C.pdf"
      },
      "width" : 399,
      "height" : 27
    },
    "1521FBA9FD2E4E9A9F5AACB71620373E" : {
      "type" : "texture",
      "index" : 3,
      "assetRequest" : {
        "type" : "slide",
        "state" : "contents",
        "slide" : "none"
      },
      "url" : {
        "native" : "assets\/6E67FEDA-4AA9-44A9-A0A3-6E04CDAAD09C.pdf"
      },
      "width" : 720,
      "height" : 405
    },
    "8CE02BDD2D81378E203A1D99B0CF6ECC" : {
      "type" : "texture",
      "index" : 0,
      "assetRequest" : {
        "type" : "slide",
        "state" : "contents",
        "slide" : "none"
      },
      "url" : {
        "native" : "assets\/6E67FEDA-4AA9-44A9-A0A3-6E04CDAAD09C.pdf"
      },
      "width" : 720,
      "height" : 405
    }
  },
  "events" : [
    {
      "effects" : [
        {
          "beginTime" : 0,
          "baseLayer" : {
            "animations" : [

            ],
            "initialState" : {
              "affineTransform" : [
                1,
                0,
                0,
                1,
                0,
                0
              ],
              "masksToBounds" : false,
              "rotation" : 0,
              "scale" : 1,
              "position" : {
                "pointX" : 360,
                "pointY" : 202.5
              },
              "width" : 720,
              "sublayerTransform" : [
                1,
                0,
                0,
                0,
                0,
                1,
                0,
                0,
                0,
                0,
                1,
                0,
                0,
                0,
                0,
                1
              ],
              "contentsRect" : {
                "y" : 0,
                "x" : 0,
                "width" : 1,
                "height" : 1
              },
              "opacity" : 1,
              "edgeAntialiasingMask" : 251658240,
              "height" : 405,
              "hidden" : false,
              "anchorPoint" : {
                "pointX" : 0.5,
                "pointY" : 0.5
              }
            },
            "objectID" : "0",
            "layers" : [
              {
                "animations" : [

                ],
                "initialState" : {
                  "affineTransform" : [
                    1,
                    0,
                    0,
                    1,
                    0,
                    0
                  ],
                  "masksToBounds" : false,
                  "rotation" : 0,
                  "scale" : 1,
                  "position" : {
                    "pointX" : 360,
                    "pointY" : 202.5
                  },
                  "width" : 720,
                  "sublayerTransform" : [
                    1,
                    0,
                    0,
                    0,
                    0,
                    1,
                    0,
                    0,
                    0,
                    0,
                    1,
                    -0.00093354433244735948,
                    0,
                    0,
                    0,
                    1
                  ],
                  "contentsRect" : {
                    "y" : 0,
                    "x" : 0,
                    "width" : 1,
                    "height" : 1
                  },
                  "opacity" : 1,
                  "edgeAntialiasingMask" : 251658240,
                  "height" : 405,
                  "hidden" : false,
                  "anchorPoint" : {
                    "pointX" : 0.5,
                    "pointY" : 0.5
                  }
                },
                "layers" : [
                  {
                    "animations" : [

                    ],
                    "layers" : [

                    ],
                    "texturedRectangle" : {
                      "isBackgroundTexture" : false,
                      "singleTextureOpacity" : 1,
                      "textureType" : 0,
                      "textBaseline" : 0,
                      "textXHeight" : 0,
                      "isVerticalText" : false
                    },
                    "initialState" : {
                      "affineTransform" : [
                        1,
                        0,
                        0,
                        1,
                        0,
                        0
                      ],
                      "masksToBounds" : false,
                      "rotation" : 0,
                      "scale" : 1,
                      "position" : {
                        "pointX" : 360,
                        "pointY" : 202.5
                      },
                      "width" : 720,
                      "sublayerTransform" : [
                        1,
                        0,
                        0,
                        0,
                        0,
                        1,
                        0,
                        0,
                        0,
                        0,
                        1,
                        0,
                        0,
                        0,
                        0,
                        1
                      ],
                      "contentsRect" : {
                        "y" : 0,
                        "x" : 0,
                        "width" : 1,
                        "height" : 1
                      },
                      "opacity" : 1,
                      "edgeAntialiasingMask" : 0,
                      "height" : 405,
                      "hidden" : false,
                      "anchorPoint" : {
                        "pointX" : 0.5,
                        "pointY" : 0.5
                      }
                    },
                    "texture" : "1521FBA9FD2E4E9A9F5AACB71620373E"
                  },
                  {
                    "animations" : [
                      {
                        "timeOffset" : 0,
                        "from" : {
                          "scalar" : false
                        },
                        "beginTime" : 0,
                        "repeatCount" : 0,
                        "fillMode" : "both",
                        "property" : "hidden",
                        "autoreverses" : false,
                        "duration" : 0.01,
                        "to" : {
                          "scalar" : true
                        }
                      }
                    ],
                    "layers" : [

                    ],
                    "texturedRectangle" : {
                      "isBackgroundTexture" : false,
                      "singleTextureOpacity" : 1,
                      "textureType" : 0,
                      "textBaseline" : 0,
                      "textXHeight" : 0,
                      "isVerticalText" : false
                    },
                    "initialState" : {
                      "affineTransform" : [
                        1,
                        0,
                        0,
                        1,
                        0,
                        0
                      ],
                      "masksToBounds" : false,
                      "rotation" : 0,
                      "scale" : 1,
                      "position" : {
                        "pointX" : 360,
                        "pointY" : 202.5
                      },
                      "width" : 720,
                      "sublayerTransform" : [
                        1,
                        0,
                        0,
                        0,
                        0,
                        1,
                        0,
                        0,
                        0,
                        0,
                        1,
                        0,
                        0,
                        0,
                        0,
                        1
                      ],
                      "contentsRect" : {
                        "y" : 0,
                        "x" : 0,
                        "width" : 1,
                        "height" : 1
                      },
                      "opacity" : 1,
                      "edgeAntialiasingMask" : 0,
                      "height" : 405,
                      "hidden" : false,
                      "anchorPoint" : {
                        "pointX" : 0.5,
                        "pointY" : 0.5
                      }
                    },
                    "texture" : "AA98C6C2E266FB093DA58C988EA7197A"
                  }
                ]
              }
            ]
          },
          "effects" : [

          ],
          "duration" : 0.01,
          "type" : "transition",
          "name" : "none",
          "objectID" : "0"
        }
      ],
      "automaticPlay" : false,
      "hyperlinks" : [

      ],
      "accessibility" : [
        {
          "text" : "What should you know to begin with?",
          "targetRectangle" : {
            "y" : 39.177164824928823,
            "x" : 161.88281176409379,
            "width" : 396.23437499999994,
            "height" : 27.21484375
          }
        },
        {
          "text" : "* ",
          "targetRectangle" : {
            "y" : 178.55708081328027,
            "x" : 357.66503832659379,
            "width" : 8.6707031249999886,
            "height" : 15.528906250000006
          }
        },
        {
          "text" : "What it does? ",
          "targetRectangle" : {
            "y" : 194.55708081328027,
            "x" : 312.80273363909379,
            "width" : 98.395312500000045,
            "height" : 15.528906250000006
          }
        },
        {
          "text" : "How? ",
          "targetRectangle" : {
            "y" : 210.55708081328027,
            "x" : 340.40390551409376,
            "width" : 43.192968749999977,
            "height" : 15.528906250000006
          }
        }
      ],
      "baseLayer" : {
        "animations" : [

        ],
        "initialState" : {
          "affineTransform" : [
            1,
            0,
            0,
            1,
            0,
            0
          ],
          "masksToBounds" : false,
          "rotation" : 0,
          "scale" : 1,
          "position" : {
            "pointX" : 360,
            "pointY" : 202.5
          },
          "width" : 720,
          "sublayerTransform" : [
            1,
            0,
            0,
            0,
            0,
            1,
            0,
            0,
            0,
            0,
            1,
            0,
            0,
            0,
            0,
            1
          ],
          "contentsRect" : {
            "y" : 0,
            "x" : 0,
            "width" : 1,
            "height" : 1
          },
          "opacity" : 1,
          "edgeAntialiasingMask" : 251658240,
          "height" : 405,
          "hidden" : false,
          "anchorPoint" : {
            "pointX" : 0.5,
            "pointY" : 0.5
          }
        },
        "objectID" : "0",
        "layers" : [
          {
            "animations" : [

            ],
            "initialState" : {
              "affineTransform" : [
                1,
                0,
                0,
                1,
                0,
                0
              ],
              "masksToBounds" : false,
              "rotation" : 0,
              "scale" : 1,
              "position" : {
                "pointX" : 360,
                "pointY" : 202.5
              },
              "width" : 720,
              "sublayerTransform" : [
                1,
                0,
                0,
                0,
                0,
                1,
                0,
                0,
                0,
                0,
                1,
                0,
                0,
                0,
                0,
                1
              ],
              "contentsRect" : {
                "y" : 0,
                "x" : 0,
                "width" : 1,
                "height" : 1
              },
              "opacity" : 1,
              "edgeAntialiasingMask" : 251658240,
              "height" : 405,
              "hidden" : false,
              "anchorPoint" : {
                "pointX" : 0.5,
                "pointY" : 0.5
              }
            },
            "layers" : [
              {
                "animations" : [

                ],
                "initialState" : {
                  "affineTransform" : [
                    1,
                    0,
                    0,
                    1,
                    0,
                    0
                  ],
                  "masksToBounds" : false,
                  "rotation" : 0,
                  "scale" : 1,
                  "position" : {
                    "pointX" : 360,
                    "pointY" : 202.5
                  },
                  "width" : 720,
                  "sublayerTransform" : [
                    1,
                    0,
                    0,
                    0,
                    0,
                    1,
                    0,
                    0,
                    0,
                    0,
                    1,
                    0,
                    0,
                    0,
                    0,
                    1
                  ],
                  "contentsRect" : {
                    "y" : 0,
                    "x" : 0,
                    "width" : 1,
                    "height" : 1
                  },
                  "opacity" : 1,
                  "edgeAntialiasingMask" : 251658240,
                  "height" : 405,
                  "hidden" : false,
                  "anchorPoint" : {
                    "pointX" : 0.5,
                    "pointY" : 0.5
                  }
                },
                "layers" : [
                  {
                    "animations" : [

                    ],
                    "layers" : [

                    ],
                    "texturedRectangle" : {
                      "isBackgroundTexture" : true,
                      "singleTextureOpacity" : 1,
                      "textureType" : 1,
                      "textBaseline" : 0,
                      "textXHeight" : 0,
                      "isVerticalText" : false
                    },
                    "initialState" : {
                      "affineTransform" : [
                        1,
                        0,
                        0,
                        1,
                        0,
                        0
                      ],
                      "masksToBounds" : false,
                      "rotation" : 0,
                      "scale" : 1,
                      "position" : {
                        "pointX" : 360,
                        "pointY" : 202.5
                      },
                      "width" : 720,
                      "sublayerTransform" : [
                        1,
                        0,
                        0,
                        0,
                        0,
                        1,
                        0,
                        0,
                        0,
                        0,
                        1,
                        0,
                        0,
                        0,
                        0,
                        1
                      ],
                      "contentsRect" : {
                        "y" : 0,
                        "x" : 0,
                        "width" : 1,
                        "height" : 1
                      },
                      "opacity" : 1,
                      "edgeAntialiasingMask" : 0,
                      "height" : 405,
                      "hidden" : false,
                      "anchorPoint" : {
                        "pointX" : 0.5,
                        "pointY" : 0.5
                      }
                    },
                    "texture" : "8CE02BDD2D81378E203A1D99B0CF6ECC"
                  }
                ]
              }
            ]
          },
          {
            "animations" : [

            ],
            "initialState" : {
              "affineTransform" : [
                1,
                0,
                0,
                1,
                0,
                0
              ],
              "masksToBounds" : false,
              "rotation" : 0,
              "scale" : 1,
              "position" : {
                "pointX" : 360,
                "pointY" : 202.5
              },
              "width" : 720,
              "sublayerTransform" : [
                1,
                0,
                0,
                0,
                0,
                1,
                0,
                0,
                0,
                0,
                1,
                0,
                0,
                0,
                0,
                1
              ],
              "contentsRect" : {
                "y" : 0,
                "x" : 0,
                "width" : 1,
                "height" : 1
              },
              "opacity" : 1,
              "edgeAntialiasingMask" : 251658240,
              "height" : 405,
              "hidden" : false,
              "anchorPoint" : {
                "pointX" : 0.5,
                "pointY" : 0.5
              }
            },
            "layers" : [
              {
                "animations" : [

                ],
                "initialState" : {
                  "affineTransform" : [
                    1,
                    0,
                    0,
                    1,
                    0,
                    0
                  ],
                  "masksToBounds" : false,
                  "rotation" : 0,
                  "scale" : 1,
                  "position" : {
                    "pointX" : 75.043303707453163,
                    "pointY" : 191.858262129656
                  },
                  "width" : 101,
                  "sublayerTransform" : [
                    1,
                    0,
                    0,
                    0,
                    0,
                    1,
                    0,
                    0,
                    0,
                    0,
                    1,
                    0,
                    0,
                    0,
                    0,
                    1
                  ],
                  "contentsRect" : {
                    "y" : 0,
                    "x" : 0,
                    "width" : 1,
                    "height" : 1
                  },
                  "opacity" : 1,
                  "edgeAntialiasingMask" : 251658240,
                  "height" : 45,
                  "hidden" : false,
                  "anchorPoint" : {
                    "pointX" : 0.5,
                    "pointY" : 0.5
                  }
                },
                "layers" : [
                  {
                    "animations" : [

                    ],
                    "layers" : [

                    ],
                    "texturedRectangle" : {
                      "singleTextureOpacity" : 1,
                      "textXHeight" : 0.13828124999999999,
                      "textBaseline" : -0.23648306378542228,
                      "isBackgroundTexture" : true,
                      "isVerticalText" : false,
                      "textColor" : [
                        0.80000001192092896,
                        0,
                        0,
                        1
                      ],
                      "textureType" : 6
                    },
                    "initialState" : {
                      "affineTransform" : [
                        1,
                        0,
                        0,
                        1,
                        0,
                        0
                      ],
                      "masksToBounds" : false,
                      "rotation" : 0,
                      "scale" : 1,
                      "position" : {
                        "pointX" : 336.95669629254684,
                        "pointY" : 33.141737870344002
                      },
                      "width" : 101,
                      "sublayerTransform" : [
                        1,
                        0,
                        0,
                        0,
                        0,
                        1,
                        0,
                        0,
                        0,
                        0,
                        1,
                        0,
                        0,
                        0,
                        0,
                        1
                      ],
                      "contentsRect" : {
                        "y" : 0,
                        "x" : 0,
                        "width" : 1,
                        "height" : 1
                      },
                      "opacity" : 1,
                      "edgeAntialiasingMask" : 0,
                      "height" : 45,
                      "hidden" : false,
                      "anchorPoint" : {
                        "pointX" : 0.5,
                        "pointY" : 0.5
                      }
                    },
                    "texture" : "62AF68723D523CB0B6126FDD444F2106"
                  }
                ]
              }
            ]
          },
          {
            "animations" : [

            ],
            "initialState" : {
              "affineTransform" : [
                1,
                0,
                0,
                1,
                0,
                0
              ],
              "masksToBounds" : false,
              "rotation" : 0,
              "scale" : 1,
              "position" : {
                "pointX" : 360,
                "pointY" : 202.5
              },
              "width" : 720,
              "sublayerTransform" : [
                1,
                0,
                0,
                0,
                0,
                1,
                0,
                0,
                0,
                0,
                1,
                0,
                0,
                0,
                0,
                1
              ],
              "contentsRect" : {
                "y" : 0,
                "x" : 0,
                "width" : 1,
                "height" : 1
              },
              "opacity" : 1,
              "edgeAntialiasingMask" : 251658240,
              "height" : 405,
              "hidden" : false,
              "anchorPoint" : {
                "pointX" : 0.5,
                "pointY" : 0.5
              }
            },
            "layers" : [
              {
                "animations" : [

                ],
                "initialState" : {
                  "affineTransform" : [
                    1,
                    0,
                    0,
                    1,
                    0,
                    0
                  ],
                  "masksToBounds" : false,
                  "rotation" : 0,
                  "scale" : 1,
                  "position" : {
                    "pointX" : 224.04330370745316,
                    "pointY" : 45.478346141304556
                  },
                  "width" : 399,
                  "sublayerTransform" : [
                    1,
                    0,
                    0,
                    0,
                    0,
                    1,
                    0,
                    0,
                    0,
                    0,
                    1,
                    0,
                    0,
                    0,
                    0,
                    1
                  ],
                  "contentsRect" : {
                    "y" : 0,
                    "x" : 0,
                    "width" : 1,
                    "height" : 1
                  },
                  "opacity" : 1,
                  "edgeAntialiasingMask" : 251658240,
                  "height" : 27,
                  "hidden" : false,
                  "anchorPoint" : {
                    "pointX" : 0.5,
                    "pointY" : 0.5
                  }
                },
                "layers" : [
                  {
                    "animations" : [

                    ],
                    "layers" : [

                    ],
                    "texturedRectangle" : {
                      "singleTextureOpacity" : 1,
                      "textXHeight" : 0.4609375,
                      "textBaseline" : 0.75207670647884528,
                      "isBackgroundTexture" : true,
                      "isVerticalText" : false,
                      "textColor" : [
                        0.9529411792755127,
                        0.9529411792755127,
                        0.9529411792755127,
                        1
                      ],
                      "textureType" : 6
                    },
                    "initialState" : {
                      "affineTransform" : [
                        1,
                        0,
                        0,
                        1,
                        0,
                        0
                      ],
                      "masksToBounds" : false,
                      "rotation" : 0,
                      "scale" : 1,
                      "position" : {
                        "pointX" : 334.95669629254684,
                        "pointY" : 22.521653858695444
                      },
                      "width" : 399,
                      "sublayerTransform" : [
                        1,
                        0,
                        0,
                        0,
                        0,
                        1,
                        0,
                        0,
                        0,
                        0,
                        1,
                        0,
                        0,
                        0,
                        0,
                        1
                      ],
                      "contentsRect" : {
                        "y" : 0,
                        "x" : 0,
                        "width" : 1,
                        "height" : 1
                      },
                      "opacity" : 1,
                      "edgeAntialiasingMask" : 0,
                      "height" : 27,
                      "hidden" : false,
                      "anchorPoint" : {
                        "pointX" : 0.5,
                        "pointY" : 0.5
                      }
                    },
                    "texture" : "81F751BA63ED0B2F87BBFEFCA49A3BD6"
                  }
                ]
              }
            ]
          }
        ]
      }
    }
  ]
}